viarag/__init__.py
viarag/client.py
viarag/filter_utils.py
viarag-0.1.3.dist-info/licenses/LICENSE.md
viarag-0.1.3.dist-info/METADATA
viarag-0.1.3.dist-info/WHEEL
viarag-0.1.3.dist-info/top_level.txt
viarag-0.1.3.dist-info/RECORD
