Metadata-Version: 2.4
Name: viarag
Version: 0.1.3
Summary: Minimal Python SDK for interacting with the ViaRAG API
Author-email: Eric Meltser <info@viaveri.co>
License: GNU General Public License v3.0
Project-URL: Homepage, https://viarag.ai
Project-URL: Repository, https://github.com/ViaVeritas/viarag
Keywords: rag,api,sdk,viarag
Classifier: Development Status :: 4 - Beta
Classifier: Intended Audience :: Developers
Classifier: License :: OSI Approved :: GNU General Public License v3 (GPLv3)
Classifier: Programming Language :: Python :: 3
Classifier: Programming Language :: Python :: 3.7
Classifier: Programming Language :: Python :: 3.8
Classifier: Programming Language :: Python :: 3.9
Classifier: Programming Language :: Python :: 3.10
Classifier: Programming Language :: Python :: 3.11
Classifier: Programming Language :: Python :: 3.12
Requires-Python: >=3.7
License-File: LICENSE.md
Requires-Dist: requests
Dynamic: license-file
